__paths__.py
notebooks/__init__.py
notebooks/pos_statistics/__init__.py
notebooks/pos_statistics/pos_statistics.ipynb
notebooks/pos_statistics/pos_statistics.py
notebooks/source/__init__.py
notebooks/source/state_on_load.py
notebooks/topic_modelling/explore.ipynb
notebooks/topic_modelling/explore.py
notebooks/word_trends/__init__.py
notebooks/word_trends/word_trends.ipynb
notebooks/word_trends/word_trends.py
humlab_disutrano-0.1.6.dist-info/METADATA
humlab_disutrano-0.1.6.dist-info/WHEEL
humlab_disutrano-0.1.6.dist-info/RECORD
