Metadata-Version: 2.1
Name: humlab-disutrano
Version: 0.1.6
Summary: Media discourses of a sustainable Norrland: journalism, places, and practices in transformation.
Home-page: https://github.com/humlab/humlab-disutrano/
License: Apache-2.0
Author: roger-mahler
Author-email: roger.mahler@hotmail.com
Requires-Python: ==3.11.*
Classifier: License :: OSI Approved :: Apache Software License
Classifier: Operating System :: OS Independent
Classifier: Programming Language :: Python
Classifier: Programming Language :: Python :: 3
Classifier: Programming Language :: Python :: 3.11
Classifier: Topic :: Software Development
Requires-Dist: bokeh (>=3.3.4,<4.0.0)
Requires-Dist: click (>=8.1.7,<9.0.0)
Requires-Dist: humlab-penelope[full] (>=0.8.1,<0.9.0)
Requires-Dist: ipydatagrid (>=1.2.1,<2.0.0)
Requires-Dist: ipywidgets (>=8.1.2,<9.0.0)
Requires-Dist: jupyterlab (==3.*)
Requires-Dist: loguru (>=0.7.2,<0.8.0)
Requires-Dist: matplotlib (>=3.8.2,<4.0.0)
Requires-Dist: msgpack (>=1.0.7,<2.0.0)
Requires-Dist: networkx (>=3.2.1,<4.0.0)
Requires-Dist: nltk (>=3.8.1,<4.0.0)
Requires-Dist: pandas (==1.5.3)
Requires-Dist: pandas-bokeh (>=0.5.5,<0.6.0)
Requires-Dist: pyarrow (>=15.0.0,<16.0.0)
Requires-Dist: scikit-learn (>=1.4.1.post1,<2.0.0)
Requires-Dist: scipy (>=1.12.0,<2.0.0)
Requires-Dist: tqdm (>=4.66.2,<5.0.0)
Requires-Dist: wordcloud (>=1.9.3,<2.0.0)
Project-URL: Repository, https://github.com/humlab/humlab-disutrano/
